wcferry/__init__.py
wcferry/client.py
wcferry/roomdata_pb2.py
wcferry/wcf_pb2.py
wcferry/wxmsg.py
wcferry_aio-39.0.14.11.dist-info/METADATA
wcferry_aio-39.0.14.11.dist-info/WHEEL
wcferry_aio-39.0.14.11.dist-info/top_level.txt
wcferry_aio-39.0.14.11.dist-info/RECORD
