Metadata-Version: 2.1
Name: wcferry-aio
Version: 39.0.14.11
Summary: 一个玩微信的工具
Home-page: https://github.com/mugbya/WeChatFerry
Author: Changhua
Author-email: lichanghua0821@gmail.com
License: MIT
Project-URL: Documentation, https://wechatferry.readthedocs.io/zh/latest/index.html
Project-URL: GitHub, https://github.com/lich0821/WeChatFerry/
Platform: UNKNOWN
Classifier: Environment :: Win32 (MS Windows)
Classifier: Intended Audience :: Developers
Classifier: Intended Audience :: Customer Service
Classifier: Topic :: Communications :: Chat
Classifier: Operating System :: Microsoft :: Windows
Classifier: Programming Language :: Python
Requires-Python: >=3.8
Requires-Dist: setuptools
Requires-Dist: grpcio-tools
Requires-Dist: pynng
Requires-Dist: requests
